LICENSE
README.md
setup.cfg
setup.py
DEVCONHEART_pyecho.egg-info/PKG-INFO
DEVCONHEART_pyecho.egg-info/SOURCES.txt
DEVCONHEART_pyecho.egg-info/dependency_links.txt
DEVCONHEART_pyecho.egg-info/not-zip-safe
DEVCONHEART_pyecho.egg-info/requires.txt
DEVCONHEART_pyecho.egg-info/top_level.txt
pyecho/__init__.py
pyecho/echo.py
pyecho/echo_aux.py
pyecho/echo_error.py
pyecho/echo_io.py