Metadata-Version: 2.1
Name: DEVCONHEART_pyecho
Version: 2024.7.16
Summary: Py-Echo is a Python package providing tools for easy handling of echo images in DICOM format built on top of pydicom, NumPy, MatPlotLib and Open-CV.
Home-page: https://github.com/aalcaineo/pyecho
Author: Alejandro Alcaine, PhD
Author-email: lalcaine@usj.es
License: GNU General Public License v2.0
Keywords: Ultrasounds,Biomedical Image Analysis
Classifier: Development Status :: 4 - Beta
Classifier: Intended Audience :: Developers
Classifier: Topic :: Software Development :: Build Tools
Classifier: Programming Language :: Python :: 3
Requires-Python: >=3.10
License-File: LICENSE
Requires-Dist: pydicom>=2.3.0
Requires-Dist: matplotlib>=3.7.0
Requires-Dist: numpy>=1.23.5
Requires-Dist: opencv-python>=4.5.5.62
Requires-Dist: GDCM>=1.1
Requires-Dist: pylibjpeg>=2.0.0
Requires-Dist: pylibjpeg-libjpeg>=2.1.0
Provides-Extra: dev
Requires-Dist: twine>=5.0.0; extra == "dev"
